bmkgquake/__init__.py
bmkgquake/display_data.py
bmkgquake/extract_data.py
bmkgquake-0.1.3.dist-info/LICENSE
bmkgquake-0.1.3.dist-info/METADATA
bmkgquake-0.1.3.dist-info/WHEEL
bmkgquake-0.1.3.dist-info/top_level.txt
bmkgquake-0.1.3.dist-info/RECORD
