Metadata-Version: 2.1
Name: bmkgquake
Version: 0.1.3
Summary: This package provides a simple way to retrieve latest earthquake data in Indonesia from the official website of the Indonesian Meteorology, Climatology, and Geophysics Agency (BMKG)
Home-page: https://github.com/destin-stack/BMKGquake-fetcher-package
Author: Destin Erika Nawang Budiarti
Author-email: destinerikanb@gmail.com
Classifier: Programming Language :: Python :: 3
Classifier: License :: OSI Approved :: GNU General Public License v3 (GPLv3)
Classifier: Operating System :: OS Independent
Classifier: Development Status :: 5 - Production/Stable
Requires-Python: >=3.6
License-File: LICENSE
